bisbasic/__init__.py
bisbasic/essentials.py
bisbasic/log.py
bisbasic/options.py
bisbasic/quantizer.py
bisbasic-0.5.6.dist-info/LICENSE
bisbasic-0.5.6.dist-info/METADATA
bisbasic-0.5.6.dist-info/WHEEL
bisbasic-0.5.6.dist-info/top_level.txt
bisbasic-0.5.6.dist-info/RECORD
