Metadata-Version: 2.1
Name: bisbasic
Version: 0.5.6
Summary: Bismuth Blockchain Dependencies
Home-page: https://github.com/bismuthfoundation/Bismuth
Author: Bismuth Foundation
Author-email: admin@bismuth.cz
License: UNKNOWN
Platform: UNKNOWN
Classifier: Programming Language :: Python :: 3
Classifier: License :: OSI Approved :: GNU General Public License v3 (GPLv3)
Classifier: Operating System :: OS Independent
